{
  "_id": "a6b971d986752e37",
  "name": "Blohm & Voss River Commander (Military)",
  "type": "vehicle",
  "img": "icons/svg/explosion.svg",
  "system": {
    "vehicleType": "boat",
    "skill": "boat",
    "handling": 4,
    "speed": 25,
    "acceleration": 0,
    "body": 6,
    "armor": 4,
    "signature": 3,
    "pilot": 3,
    "sensor": 0,
    "cargo": 20,
    "load": 0,
    "seating": "Twin bucket + rear bench",
    "cost": 300000,
    "availability": "",
    "conditionMonitor": {
      "value": 0,
      "max": 10
    },
    "autonav": 3,
    "notes": "<p>The Military configuration of the River Commander river patrol boat — uparmored (Armor 4) and fitted for weapon mounts.</p><p><em>Max speed 75 m/CT (cruising 25 used for tests). IC/1,000 liters; 15 km/liter. Weapon mounts. Seagoing variant +25,000¥. Rigger Black Book p.69.</em></p>"
  },
  "prototypeToken": {
    "name": "Blohm & Voss River Commander (Military)",
    "displayName": 20,
    "actorLink": false,
    "width": 2,
    "height": 1,
    "texture": {
      "src": "icons/svg/explosion.svg",
      "scaleX": 1,
      "scaleY": 1
    },
    "disposition": 0,
    "displayBars": 0
  },
  "effects": [],
  "folder": null,
  "sort": 0,
  "flags": {},
  "_stats": {
    "coreVersion": "13.351",
    "systemId": "sr2e",
    "systemVersion": "0.1.0",
    "createdTime": 1782200000000,
    "modifiedTime": 1782200000000,
    "lastModifiedBy": null,
    "compendiumSource": null,
    "duplicateSource": null,
    "exportSource": null
  },
  "ownership": {
    "default": 0
  },
  "_key": "!actors!a6b971d986752e37"
}
